setup.py
Cake/__init__.py
btc_py.egg-info/PKG-INFO
btc_py.egg-info/SOURCES.txt
btc_py.egg-info/dependency_links.txt
btc_py.egg-info/not-zip-safe
btc_py.egg-info/top_level.txt