Metadata-Version: 1.0
Name: btc-py
Version: 0.3
Summary: scraping bitcoin values
Home-page: https://www.github.com/Alvixeon/btc-py
Author: Alvixeon
Author-email: remusername@gmail.com
License: MIT
Platform: UNKNOWN
